icgen/__init__.py
icgen/dataset_names.py
icgen/download.py
icgen/icgen.py
icgen/infos/binary_alpha_digits.json
icgen/infos/caltech101.json
icgen/infos/caltech_birds2010.json
icgen/infos/caltech_birds2011.json
icgen/infos/cars196.json
icgen/infos/cassava.json
icgen/infos/cats_vs_dogs.json
icgen/infos/cifar10.json
icgen/infos/cifar100.json
icgen/infos/cifar10_1.json
icgen/infos/citrus_leaves.json
icgen/infos/cmaterdb/bangla.json
icgen/infos/cmaterdb/devanagari.json
icgen/infos/cmaterdb/telugu.json
icgen/infos/coil100.json
icgen/infos/colorectal_histology.json
icgen/infos/cycle_gan/apple2orange.json
icgen/infos/cycle_gan/facades.json
icgen/infos/cycle_gan/horse2zebra.json
icgen/infos/cycle_gan/iphone2dslr_flower.json
icgen/infos/cycle_gan/maps.json
icgen/infos/cycle_gan/summer2winter_yosemite.json
icgen/infos/cycle_gan/ukiyoe2photo.json
icgen/infos/cycle_gan/vangogh2photo.json
icgen/infos/deep_weeds.json
icgen/infos/emnist/balanced.json
icgen/infos/emnist/byclass.json
icgen/infos/emnist/mnist.json
icgen/infos/eurosat/rgb.json
icgen/infos/fashion_mnist.json
icgen/infos/horses_or_humans.json
icgen/infos/imagenet_resized/32x32.json
icgen/infos/imagenette.json
icgen/infos/kmnist.json
icgen/infos/malaria.json
icgen/infos/mnist.json
icgen/infos/omniglot.json
icgen/infos/oxford_flowers102.json
icgen/infos/oxford_iiit_pet.json
icgen/infos/plant_village.json
icgen/infos/rock_paper_scissors.json
icgen/infos/stanford_dogs.json
icgen/infos/svhn_cropped.json
icgen/infos/tf_flowers.json
icgen/infos/uc_merced.json
icgen/infos/visual_domain_decathlon/aircraft.json
icgen/infos/visual_domain_decathlon/daimlerpedcls.json
icgen/infos/visual_domain_decathlon/dtd.json
icgen/infos/visual_domain_decathlon/gtsrb.json
icgen/infos/visual_domain_decathlon/ucf101.json
icgen/infos/visual_domain_decathlon/vgg-flowers.json
icgen/torch_utils.py
icgen-0.3.0.dist-info/LICENSE
icgen-0.3.0.dist-info/WHEEL
icgen-0.3.0.dist-info/METADATA
icgen-0.3.0.dist-info/RECORD
