Metadata-Version: 2.1
Name: icgen
Version: 0.3.0
Summary:  Image Classification Dataset Generator
Home-page: https://github.com/automl/ICGen
License: MIT
Author: Danny Stoll
Requires-Python: >=3.6.1,<4.0.0
Classifier: License :: OSI Approved :: MIT License
Classifier: Programming Language :: Python :: 3
Classifier: Programming Language :: Python :: 3.7
Classifier: Programming Language :: Python :: 3.8
Requires-Dist: PILLOW (>=7.1.2,<8.0.0)
Requires-Dist: more_itertools (>=8.4.0,<9.0.0)
Requires-Dist: opencv-python (>=4.2.0,<5.0.0)
Requires-Dist: tensorflow (>=2.2.0,<3.0.0)
Requires-Dist: tensorflow_datasets (==2.1.0)
Requires-Dist: torch (>=1.5.1,<2.0.0)
Project-URL: Repository, https://github.com/automl/ICGen
